pyquest/__init__.py
pyquest/constants.py
pyquest/display_keys.py
pyquest/main.py
pyquest/monitor_clipboard.py
pyquest/monitor_keystrokes.py
pyquest/monitor_prompt_toolkit_fix1_space.py
pyquest/monitor_prompt_toolkit_fix2_printable.py
pyquest/monitor_prompt_toolkit_fix3_printable_ctrlv_insert.py
pyquest/monitor_prompt_toolkit_fix4_any.py
pyquest/monitor_prompt_toolkit_fix5_aider_refactor.py
pyquest/monitor_prompt_toolkit_fixed_space_not_paste.py
pyquest/monitor_transform_keystrokes.py
pyquest/util.py
ipython_quest-0.1.1.dist-info/METADATA
ipython_quest-0.1.1.dist-info/WHEEL
ipython_quest-0.1.1.dist-info/entry_points.txt
ipython_quest-0.1.1.dist-info/RECORD
